數位系統導論 實驗/Lab9/demo作業/HW1/lab9_hw.v
//以前者(1ns)為單位，以後者(1ps)的時間，查看一次電路的行為
`timescale 1ns/1ps

//宣告module名稱,輸出入名稱
module lab9_hw(
	CLK, 
	RST, 
	in_a, 
	in_b, 
	Product, 
	Product_Valid
);
// in_a * in_b = Product
// in_a is Multiplicand , in_b is Multiplier
					
//定義port, 包含input, output
input 			CLK, RST;
input 	[7:0]	in_a;			// Multiplicand
input 	[7:0]	in_b;			// Multiplier
output 	[15:0]  Product;
output  		Product_Valid;

reg 	[15:0]	Mplicand;		//被乘數
reg 	[7:0]	Mplier;			//乘數
reg 	[15:0]	Product;
reg 			Product_Valid;
reg 	[5:0]	Counter ;
reg				sign;			//正負號判斷 (signed)

//Counter
always @(posedge CLK or posedge RST)
begin
	if(RST)
		Counter <= 6'b0;
	else
		Counter <= Counter + 6'b1;

end

//Product
always @(posedge CLK or posedge RST)
begin	
	//初始化數值
	if(RST) begin
		Product  <= 16'b0;
		Mplicand <= 16'b0;
		Mplier   <= 8'b0;		
	end 
	//輸入乘數與被乘數
	else if(Counter == 6'd0) begin
		Product	 	<= Product + {8'b0 , in_b};
		Mplicand 	<= {8'b0,in_a};
		Mplier	 	<= in_b;		
	end 
	//乘法與數值移位
	else if(Counter <=6'd8) //執行八次
	begin				
		if(Product[0] == 1'b1)begin
			Product <= Product + {Mplicand , 8'b0} >> 1'b1;
		end
		else begin
			Product <= Product >> 1'b1;
		end
	end 
	else begin
		Product 	<= Product;
		Mplicand	<= Mplicand;
		Mplier 		<= Mplier;
	end
end

//Product_Valid
always @(posedge CLK or posedge RST)
begin
	if(RST)
		Product_Valid <=1'b0;
	else if(Counter==6'd9)
		Product_Valid <=1'b1;
	else
		Product_Valid <=1'b0;
end

endmodule

數位系統導論 實驗/Lab9/demo作業/HW1/tb_lab9_hw_unsigned.v
`timescale 1ns/1ps
`include "lab9_hw.v" //這裡要記得改成要測試.v檔

//`define SEED 120
module tb_lab9();


reg [7:0]	in_a;
reg [7:0]	in_b;
reg 		CLK;
reg			reset;

wire [15:0]	out;
wire 		out_valid;
reg [5:0]	count;
reg	[15:0]	correct_ans;
reg 		error;
//integer seed;

reg [7:0]	temp_a;
reg [7:0]	temp_b;

lab9_hw m1(CLK, reset, in_a, in_b, out, out_valid);

initial begin

	$dumpfile("lab9_hw_unsigned.vcd");  // gtkwave
	$dumpvars;
	CLK = 1'b0;
	#20 reset = 1;
		temp_a = 8'd3;
		temp_b = 8'd9;
	#20 reset = 0;


	#700 reset = 1;
		temp_a = 8'd25;
		temp_b = 8'd0;
	#20 reset = 0;


	#700 reset = 1;
		temp_a = 8'd100;
		temp_b = 8'd14;
	#20 reset = 0;

	#700 reset = 1;
		temp_a = 8'd123;
		temp_b = 8'd12;
	#20 reset = 0;

	#700 reset = 1;
		temp_a = 8'd45;
		temp_b = 8'd69;
	#20 reset = 0;


	#20 reset = 0;
	#700 $finish;


end

always #10 CLK = ~CLK;

	always @(posedge CLK or posedge reset)
	begin
		if(reset)
		begin
			count <= 0;
			in_a <= temp_a;
			in_b <= temp_b;
			correct_ans <= 0;
			error <= 0;
		end

		else
		begin
			correct_ans <= in_a * in_b;
			count <= count +1;

			if(out_valid==1)
				if(out != correct_ans)
				begin
					error <=1;
					$display ();
					$display ("//////////");
					$display ("// Fail //");
					$display ("//////////");
					$display ("doing %d * %d ...",temp_a, temp_b);
					$display ("your answer is %d, but correct answer is %d\n",
					out, correct_ans);
					$display ();
				end
				else
				begin
					error <= 0;
					$display ();
					$display ("////////////////");
					$display ("// Successful //");
					$display ("////////////////");
					$display ("doing %d * %d ...",temp_a, temp_b);
					$display ("your answer is %d,  correct answer is %d\n",
					out, correct_ans);
					$display ();
				end
		end
	end

endmodule

數位系統導論 實驗/Lab9/demo作業/HW1/lab9_hw_unsigned.vcd
$date
	Mon Jun  8 16:50:53 2020
$end
$version
	Icarus Verilog
$end
$timescale
	1ps
$end
$scope module tb_lab9 $end
$var wire 1 ! out_valid $end
$var wire 16 " out [15:0] $end
$var reg 1 # CLK $end
$var reg 16 $ correct_ans [15:0] $end
$var reg 6 % count [5:0] $end
$var reg 1 & error $end
$var reg 8 ' in_a [7:0] $end
$var reg 8 ( in_b [7:0] $end
$var reg 1 ) reset $end
$var reg 8 * temp_a [7:0] $end
$var reg 8 + temp_b [7:0] $end
$scope module m1 $end
$var wire 1 # CLK $end
$var wire 1 ) RST $end
$var wire 8 , in_a [7:0] $end
$var wire 8 - in_b [7:0] $end
$var reg 6 . Counter [5:0] $end
$var reg 16 / Mplicand [15:0] $end
$var reg 8 0 Mplier [7:0] $end
$var reg 16 1 Product [15:0] $end
$var reg 1 ! Product_Valid $end
$upscope $end
$upscope $end
$enddefinitions $end
#0
$dumpvars
bx 1
bx 0
bx /
bx .
bx -
bx ,
bx +
bx *
x)
bx (
bx '
x&
bx %
bx $
0#
bx "
x!
$end
#10000
0!
1#
#20000
0&
b0 $
b1001 (
b1001 -
b11 '
b11 ,
b0 %
b0 0
b0 /
b0 "
b0 1
b0 .
0#
b1001 +
b11 *
1)
#30000
1#
#40000
0#
0)
#50000
b1 %
b11011 $
b1001 0
b11 /
b1001 "
b1001 1
b1 .
1#
#60000
0#
#70000
b10 .
b110000100 "
b110000100 1
b10 %
1#
#80000
0#
#90000
b11 %
b11000010 "
b11000010 1
b11 .
1#
#100000
0#
#110000
b100 .
b1100001 "
b1100001 1
b100 %
1#
#120000
0#
#130000
b101 %
b110110000 "
b110110000 1
b101 .
1#
#140000
0#
#150000
b110 .
b11011000 "
b11011000 1
b110 %
1#
#160000
0#
#170000
b111 %
b1101100 "
b1101100 1
b111 .
1#
#180000
0#
#190000
b1000 .
b110110 "
b110110 1
b1000 %
1#
#200000
0#
#210000
b1001 %
b11011 "
b11011 1
b1001 .
1#
#220000
0#
#230000
b1010 .
1!
b1010 %
1#
#240000
0#
#250000
b1011 %
0!
b1011 .
1#
#260000
0#
#270000
b1100 .
b1100 %
1#
#280000
0#
#290000
b1101 %
b1101 .
1#
#300000
0#
#310000
b1110 .
b1110 %
1#
#320000
0#
#330000
b1111 %
b1111 .
1#
#340000
0#
#350000
b10000 .
b10000 %
1#
#360000
0#
#370000
b10001 %
b10001 .
1#
#380000
0#
#390000
b10010 .
b10010 %
1#
#400000
0#
#410000
b10011 %
b10011 .
1#
#420000
0#
#430000
b10100 .
b10100 %
1#
#440000
0#
#450000
b10101 %
b10101 .
1#
#460000
0#
#470000
b10110 .
b10110 %
1#
#480000
0#
#490000
b10111 %
b10111 .
1#
#500000
0#
#510000
b11000 .
b11000 %
1#
#520000
0#
#530000
b11001 %
b11001 .
1#
#540000
0#
#550000
b11010 .
b11010 %
1#
#560000
0#
#570000
b11011 %
b11011 .
1#
#580000
0#
#590000
b11100 .
b11100 %
1#
#600000
0#
#610000
b11101 %
b11101 .
1#
#620000
0#
#630000
b11110 .
b11110 %
1#
#640000
0#
#650000
b11111 %
b11111 .
1#
#660000
0#
#670000
b100000 .
b100000 %
1#
#680000
0#
#690000
b100001 %
b100001 .
1#
#700000
0#
#710000
b100010 .
b100010 %
1#
#720000
0#
#730000
b100011 %
b100011 .
1#
#740000
b0 .
b0 0
b0 /
b0 "
b0 1
b0 $
b0 (
b0 -
b11001 '
b11001 ,
b0 %
0#
b0 +
b11001 *
1)
#750000
1#
#760000
0#
0)
#770000
b1 .
b11001 /
b1 %
1#
#780000
0#
#790000
b10 %
b10 .
1#
#800000
0#
#810000
b11 .
b11 %
1#
#820000
0#
#830000
b100 %
b100 .
1#
#840000
0#
#850000
b101 .
b101 %
1#
#860000
0#
#870000
b110 %
b110 .
1#
#880000
0#
#890000
b111 .
b111 %
1#
#900000
0#
#910000
b1000 %
b1000 .
1#
#920000
0#
#930000
b1001 .
b1001 %
1#
#940000
0#
#950000
b1010 %
1!
b1010 .
1#
#960000
0#
#970000
b1011 .
0!
b1011 %
1#
#980000
0#
#990000
b1100 %
b1100 .
1#
#1000000
0#
#1010000
b1101 .
b1101 %
1#
#1020000
0#
#1030000
b1110 %
b1110 .
1#
#1040000
0#
#1050000
b1111 .
b1111 %
1#
#1060000
0#
#1070000
b10000 %
b10000 .
1#
#1080000
0#
#1090000
b10001 .
b10001 %
1#
#1100000
0#
#1110000
b10010 %
b10010 .
1#
#1120000
0#
#1130000
b10011 .
b10011 %
1#
#1140000
0#
#1150000
b10100 %
b10100 .
1#
#1160000
0#
#1170000
b10101 .
b10101 %
1#
#1180000
0#
#1190000
b10110 %
b10110 .
1#
#1200000
0#
#1210000
b10111 .
b10111 %
1#
#1220000
0#
#1230000
b11000 %
b11000 .
1#
#1240000
0#
#1250000
b11001 .
b11001 %
1#
#1260000
0#
#1270000
b11010 %
b11010 .
1#
#1280000
0#
#1290000
b11011 .
b11011 %
1#
#1300000
0#
#1310000
b11100 %
b11100 .
1#
#1320000
0#
#1330000
b11101 .
b11101 %
1#
#1340000
0#
#1350000
b11110 %
b11110 .
1#
#1360000
0#
#1370000
b11111 .
b11111 %
1#
#1380000
0#
#1390000
b100000 %
b100000 .
1#
#1400000
0#
#1410000
b100001 .
b100001 %
1#
#1420000
0#
#1430000
b100010 %
b100010 .
1#
#1440000
0#
#1450000
b100011 .
b100011 %
1#
#1460000
b1110 (
b1110 -
b1100100 '
b1100100 ,
b0 %
b0 /
b0 .
0#
b1110 +
b1100100 *
1)
#1470000
1#
#1480000
0#
0)
#1490000
b1 %
b10101111000 $
b1110 0
b1100100 /
b1110 "
b1110 1
b1 .
1#
#1500000
0#
#1510000
b10 .
b111 "
b111 1
b10 %
1#
#1520000
0#
#1530000
b11 %
b11001000000011 "
b11001000000011 1
b11 .
1#
#1540000
0#
#1550000
b100 .
b100101100000001 "
b100101100000001 1
b100 %
1#
#1560000
0#
#1570000
b101 %
b101011110000000 "
b101011110000000 1
b101 .
1#
#1580000
0#
#1590000
b110 .
b10101111000000 "
b10101111000000 1
b110 %
1#
#1600000
0#
#1610000
b111 %
b1010111100000 "
b1010111100000 1
b111 .
1#
#1620000
0#
#1630000
b1000 .
b101011110000 "
b101011110000 1
b1000 %
1#
#1640000
0#
#1650000
b1001 %
b10101111000 "
b10101111000 1
b1001 .
1#
#1660000
0#
#1670000
b1010 .
1!
b1010 %
1#
#1680000
0#
#1690000
b1011 %
0!
b1011 .
1#
#1700000
0#
#1710000
b1100 .
b1100 %
1#
#1720000
0#
#1730000
b1101 %
b1101 .
1#
#1740000
0#
#1750000
b1110 .
b1110 %
1#
#1760000
0#
#1770000
b1111 %
b1111 .
1#
#1780000
0#
#1790000
b10000 .
b10000 %
1#
#1800000
0#
#1810000
b10001 %
b10001 .
1#
#1820000
0#
#1830000
b10010 .
b10010 %
1#
#1840000
0#
#1850000
b10011 %
b10011 .
1#
#1860000
0#
#1870000
b10100 .
b10100 %
1#
#1880000
0#
#1890000
b10101 %
b10101 .
1#
#1900000
0#
#1910000
b10110 .
b10110 %
1#
#1920000
0#
#1930000
b10111 %
b10111 .
1#
#1940000
0#
#1950000
b11000 .
b11000 %
1#
#1960000
0#
#1970000
b11001 %
b11001 .
1#
#1980000
0#
#1990000
b11010 .
b11010 %
1#
#2000000
0#
#2010000
b11011 %
b11011 .
1#
#2020000
0#
#2030000
b11100 .
b11100 %
1#
#2040000
0#
#2050000
b11101 %
b11101 .
1#
#2060000
0#
#2070000
b11110 .
b11110 %
1#
#2080000
0#
#2090000
b11111 %
b11111 .
1#
#2100000
0#
#2110000
b100000 .
b100000 %
1#
#2120000
0#
#2130000
b100001 %
b100001 .
1#
#2140000
0#
#2150000
b100010 .
b100010 %
1#
#2160000
0#
#2170000
b100011 %
b100011 .
1#
#2180000
b0 .
b0 0
b0 /
b0 "
b0 1
b0 $
b1100 (
b1100 -
b1111011 '
b1111011 ,
b0 %
0#
b1100 +
b1111011 *
1)
#2190000
1#
#2200000
0#
0)
#2210000
b1 .
b1100 0
b1111011 /
b1100 "
b1100 1
b1 %
b10111000100 $
1#
#2220000
0#
#2230000
b10 %
b110 "
b110 1
b10 .
1#
#2240000
0#
#2250000
b11 .
b11 "
b11 1
b11 %
1#
#2260000
0#
#2270000
b100 %
b11110110000001 "
b11110110000001 1
b100 .
1#
#2280000
0#
#2290000
b101 .
b101110001000000 "
b101110001000000 1
b101 %
1#
#2300000
0#
#2310000
b110 %
b10111000100000 "
b10111000100000 1
b110 .
1#
#2320000
0#
#2330000
b111 .
b1011100010000 "
b1011100010000 1
b111 %
1#
#2340000
0#
#2350000
b1000 %
b101110001000 "
b101110001000 1
b1000 .
1#
#2360000
0#
#2370000
b1001 .
b10111000100 "
b10111000100 1
b1001 %
1#
#2380000
0#
#2390000
b1010 %
1!
b1010 .
1#
#2400000
0#
#2410000
b1011 .
0!
b1011 %
1#
#2420000
0#
#2430000
b1100 %
b1100 .
1#
#2440000
0#
#2450000
b1101 .
b1101 %
1#
#2460000
0#
#2470000
b1110 %
b1110 .
1#
#2480000
0#
#2490000
b1111 .
b1111 %
1#
#2500000
0#
#2510000
b10000 %
b10000 .
1#
#2520000
0#
#2530000
b10001 .
b10001 %
1#
#2540000
0#
#2550000
b10010 %
b10010 .
1#
#2560000
0#
#2570000
b10011 .
b10011 %
1#
#2580000
0#
#2590000
b10100 %
b10100 .
1#
#2600000
0#
#2610000
b10101 .
b10101 %
1#
#2620000
0#
#2630000
b10110 %
b10110 .
1#
#2640000
0#
#2650000
b10111 .
b10111 %
1#
#2660000
0#
#2670000
b11000 %
b11000 .
1#
#2680000
0#
#2690000
b11001 .
b11001 %
1#
#2700000
0#
#2710000
b11010 %
b11010 .
1#
#2720000
0#
#2730000
b11011 .
b11011 %
1#
#2740000
0#
#2750000
b11100 %
b11100 .
1#
#2760000
0#
#2770000
b11101 .
b11101 %
1#
#2780000
0#
#2790000
b11110 %
b11110 .
1#
#2800000
0#
#2810000
b11111 .
b11111 %
1#
#2820000
0#
#2830000
b100000 %
b100000 .
1#
#2840000
0#
#2850000
b100001 .
b100001 %
1#
#2860000
0#
#2870000
b100010 %
b100010 .
1#
#2880000
0#
#2890000
b100011 .
b100011 %
1#
#2900000
b0 $
b1000101 (
b1000101 -
b101101 '
b101101 ,
b0 %
b0 0
b0 /
b0 "
b0 1
b0 .
0#
b1000101 +
b101101 *
1)
#2910000
1#
#2920000
0#
0)
#2930000
b1 %
b110000100001 $
b1000101 0
b101101 /
b1000101 "
b1000101 1
b1 .
1#
#2940000
0#
#2950000
b10 .
b1011010100010 "
b1011010100010 1
b10 %
1#
#2960000
0#
#2970000
b11 %
b101101010001 "
b101101010001 1
b11 .
1#
#2980000
0#
#2990000
b100 .
b1110000101000 "
b1110000101000 1
b100 %
1#
#3000000
0#
#3010000
b101 %
b111000010100 "
b111000010100 1
b101 .
1#
#3020000
0#
#3030000
b110 .
b11100001010 "
b11100001010 1
b110 %
1#
#3040000
0#
#3050000
b111 %
b1110000101 "
b1110000101 1
b111 .
1#
#3060000
0#
#3070000
b1000 .
b1100001000010 "
b1100001000010 1
b1000 %
1#
#3080000
0#
#3090000
b1001 %
b110000100001 "
b110000100001 1
b1001 .
1#
#3100000
0#
#3110000
b1010 .
1!
b1010 %
1#
#3120000
0#
#3130000
b1011 %
0!
b1011 .
1#
#3140000
0#
#3150000
b1100 .
b1100 %
1#
#3160000
0#
#3170000
b1101 %
b1101 .
1#
#3180000
0#
#3190000
b1110 .
b1110 %
1#
#3200000
0#
#3210000
b1111 %
b1111 .
1#
#3220000
0#
#3230000
b10000 .
b10000 %
1#
#3240000
0#
#3250000
b10001 %
b10001 .
1#
#3260000
0#
#3270000
b10010 .
b10010 %
1#
#3280000
0#
#3290000
b10011 %
b10011 .
1#
#3300000
0#
#3310000
b10100 .
b10100 %
1#
#3320000
0#
#3330000
b10101 %
b10101 .
1#
#3340000
0#
#3350000
b10110 .
b10110 %
1#
#3360000
0#
#3370000
b10111 %
b10111 .
1#
#3380000
0#
#3390000
b11000 .
b11000 %
1#
#3400000
0#
#3410000
b11001 %
b11001 .
1#
#3420000
0#
#3430000
b11010 .
b11010 %
1#
#3440000
0#
#3450000
b11011 %
b11011 .
1#
#3460000
0#
#3470000
b11100 .
b11100 %
1#
#3480000
0#
#3490000
b11101 %
b11101 .
1#
#3500000
0#
#3510000
b11110 .
b11110 %
1#
#3520000
0#
#3530000
b11111 %
b11111 .
1#
#3540000
0#
#3550000
b100000 .
b100000 %
1#
#3560000
0#
#3570000
b100001 %
b100001 .
1#
#3580000
0#
#3590000
b100010 .
b100010 %
1#
#3600000
0#
#3610000
b100011 %
b100011 .
1#
#3620000
0#
#3630000
b100100 .
b100100 %
1#
