數位系統導論 實驗/DD3/demo_add4.v
module add4(a, b, c, d, sum, ov);

	input [3:0] a, b, c, d;
	output reg [3:0] sum;
	output reg ov;
	output reg s1,s0;
	
	always @(a or b or c or d)begin
		
		case(a)
			4'b1000: sum <= 4'b0011;		//a=8
			4'b1001: sum <= 4'b0011;		//a=9
			default: {s1, s0, sum} = a + b + c + d;
		endcase
		
		ov <= s1|s0;
	end
endmodule

數位系統導論 實驗/DD3/testbench_add4_2w.v
`timescale 1ns / 1ps
module testbench_add4;

reg [3:0] a, b, c, d;
wire [3:0] sum;
wire ov;
reg clk;
reg	rst;
reg [3:0] correct_sum;
reg [6:0] test_num;
reg correct_ov;
reg ov1 , ov2;

always #5 clk = ~clk;
always #5 rst = ~rst;

add4 DUT(a, b, c, d, sum, ov);

initial
begin
	clk <= 0;
	rst <= 0;
	a <= 0; 
	b <= 0;
	c <= 0;
	d <= 0;
	test_num <= 0;
	$dumpfile("add4.vcd");
	$dumpvars;
end

always@(posedge clk or negedge rst)
begin
	if(rst)begin
	
		if(a <= 15) begin 
			a <= a + 1;
			test_num <= test_num + 1;
		end 
		if(a == 15) begin
			b <= b + 1;
		end
		if(b == 15 && a == 15) begin
			b <= b + 1;
			c <= c + 1;
		end
		d <= {$random} % 16;

	end
	else begin
		{ov1 , ov2 , correct_sum} = a + b + c + d;
		correct_ov = ov1 || ov2;
		if({ov, sum} != {correct_ov, correct_sum}) begin
			$display ("Test %d ", test_num);
			$display ("/////////////////////");
			$display ("////////Fail!////////");
			$display ("/////////////////////");
			$display ("%d + %d + %d + %d = ?", a, b, c, d);
			$display ("your answer: ov = %d, sum = %d", ov, sum);
			$display ("correct answer: ov = %d, sum = %d", correct_ov, correct_sum);
			$display ("\n");
		end
		else begin
			$display ("Test %d ", test_num);
			$display ("/////////////////////");
			$display ("////////Fail!////////");
			$display ("/////////////////////");
			$display ("%d + %d + %d + %d = ?", a, b, c, d);
			$display ("your answer: ov = %d, sum = %d", ov, sum);
			$display ("correct answer: ov = %d, sum = %d", correct_ov, correct_sum);
			$display ("\n");
		end
	end
end
initial #1005 $finish;
endmodule

數位系統導論 實驗/DD2/add4.vcd
$date
	Sat Apr 11 06:59:04 2020
$end
$version
	Icarus Verilog
$end
$timescale
	1ps
$end
$scope module testbench_add4 $end
$var wire 1 ! ov $end
$var wire 4 " sum [3:0] $end
$var reg 4 # a [3:0] $end
$var reg 4 $ b [3:0] $end
$var reg 4 % c [3:0] $end
$var reg 1 & clk $end
$var reg 1 ' correct_ov $end
$var reg 4 ( correct_sum [3:0] $end
$var reg 4 ) d [3:0] $end
$var reg 1 * ov1 $end
$var reg 1 + ov2 $end
$var reg 1 , rst $end
$var reg 7 - test_num [6:0] $end
$scope module DUT $end
$var wire 4 . a [3:0] $end
$var wire 4 / b [3:0] $end
$var wire 4 0 c [3:0] $end
$var wire 4 1 d [3:0] $end
$var reg 1 2 ov $end
$var reg 1 3 s0 $end
$var reg 1 4 s1 $end
$var reg 4 5 sum [3:0] $end
$upscope $end
$upscope $end
$enddefinitions $end
#0
$dumpvars
b0 5
04
03
02
b0 1
b0 0
b0 /
b0 .
b0 -
0,
0+
0*
b0 )
b0 (
0'
0&
b0 %
b0 $
b0 #
b0 "
0!
$end
#5000
b101 5
b101 "
b100 )
b100 1
b1 -
b1 #
b1 .
1,
1&
#10000
b101 (
0,
0&
#15000
b11 5
b11 "
b1 )
b1 1
b10 -
b10 #
b10 .
1,
1&
#20000
b11 (
0,
0&
#25000
b1100 5
b1100 "
b1001 )
b1001 1
b11 -
b11 #
b11 .
1,
1&
#30000
b1100 (
0,
0&
#35000
b111 5
b111 "
b11 )
b11 1
b100 -
b100 #
b100 .
1,
1&
#40000
b111 (
0,
0&
#45000
12
1!
13
b10 5
b10 "
b1101 )
b1101 1
b101 -
b101 #
b101 .
1,
1&
#50000
1'
1+
b10 (
0,
0&
#55000
b11 5
b11 "
b110 -
b110 #
b110 .
1,
1&
#60000
b11 (
0,
0&
#65000
02
0!
03
b1100 5
b1100 "
b101 )
b101 1
b111 -
b111 #
b111 .
1,
1&
#70000
0'
0+
b1100 (
0,
0&
#75000
b11 5
b11 "
b10 )
b10 1
b1000 -
b1000 #
b1000 .
1,
1&
#80000
b1010 (
0,
0&
#85000
b1 )
b1 1
b1001 -
b1001 #
b1001 .
1,
1&
#90000
0,
0&
#95000
12
1!
13
b111 5
b111 "
b1101 )
b1101 1
b1010 -
b1010 #
b1010 .
1,
1&
#100000
1'
1+
b111 (
0,
0&
#105000
b1 5
b1 "
b110 )
b110 1
b1011 -
b1011 #
b1011 .
1,
1&
#110000
b1 (
0,
0&
#115000
b1001 5
b1001 "
b1101 )
b1101 1
b1100 -
b1100 #
b1100 .
1,
1&
#120000
b1001 (
0,
0&
#125000
b1010 5
b1010 "
b1101 -
b1101 #
b1101 .
1,
1&
#130000
b1010 (
0,
0&
#135000
b1100 )
b1100 1
b1110 -
b1110 #
b1110 .
1,
1&
#140000
0,
0&
#145000
b1000 5
b1000 "
b1001 )
b1001 1
b1111 -
b1111 #
b1111 .
1,
1&
#150000
b1000 (
0,
0&
#155000
02
0!
03
b111 5
b111 "
b110 )
b110 1
b1 $
b1 /
b10000 -
b0 #
b0 .
1,
1&
#160000
0'
0+
b111 (
0,
0&
#165000
b101 )
b101 1
b10001 -
b1 #
b1 .
1,
1&
#170000
0,
0&
#175000
b1101 5
b1101 "
b1010 )
b1010 1
b10010 -
b10 #
b10 .
1,
1&
#180000
b1101 (
0,
0&
#185000
b1001 5
b1001 "
b101 )
b101 1
b10011 -
b11 #
b11 .
1,
1&
#190000
b1001 (
0,
0&
#195000
b1100 5
b1100 "
b111 )
b111 1
b10100 -
b100 #
b100 .
1,
1&
#200000
b1100 (
0,
0&
#205000
b1000 5
b1000 "
b10 )
b10 1
b10101 -
b101 #
b101 .
1,
1&
#210000
b1000 (
0,
0&
#215000
12
1!
13
b110 5
b110 "
b1111 )
b1111 1
b10110 -
b110 #
b110 .
1,
1&
#220000
1'
1+
b110 (
0,
0&
#225000
02
0!
03
b1010 5
b1010 "
b10 )
b10 1
b10111 -
b111 #
b111 .
1,
1&
#230000
0'
0+
b1010 (
0,
0&
#235000
b11 5
b11 "
b1110 )
b1110 1
b11000 -
b1000 #
b1000 .
1,
1&
#240000
1'
1+
b111 (
0,
0&
#245000
b1000 )
b1000 1
b11001 -
b1001 #
b1001 .
1,
1&
#250000
b10 (
0,
0&
#255000
12
1!
13
b0 5
b0 "
b101 )
b101 1
b11010 -
b1010 #
b1010 .
1,
1&
#260000
b0 (
0,
0&
#265000
b1000 5
b1000 "
b1100 )
b1100 1
b11011 -
b1011 #
b1011 .
1,
1&
#270000
b1000 (
0,
0&
#275000
b1010 5
b1010 "
b1101 )
b1101 1
b11100 -
b1100 #
b1100 .
1,
1&
#280000
b1010 (
0,
0&
#285000
b1011 5
b1011 "
b11101 -
b1101 #
b1101 .
1,
1&
#290000
b1011 (
0,
0&
#295000
b100 5
b100 "
b101 )
b101 1
b11110 -
b1110 #
b1110 .
1,
1&
#300000
b100 (
0,
0&
#305000
b11 5
b11 "
b11 )
b11 1
b11111 -
b1111 #
b1111 .
1,
1&
#310000
b11 (
0,
0&
#315000
02
0!
03
b1100 5
b1100 "
b1010 )
b1010 1
b10 $
b10 /
b100000 -
b0 #
b0 .
1,
1&
#320000
0'
0+
b1100 (
0,
0&
#325000
b11 5
b11 "
b0 )
b0 1
b100001 -
b1 #
b1 .
1,
1&
#330000
b11 (
0,
0&
#335000
b100 5
b100 "
b100010 -
b10 #
b10 .
1,
1&
#340000
b100 (
0,
0&
#345000
b1111 5
b1111 "
b1010 )
b1010 1
b100011 -
b11 #
b11 .
1,
1&
#350000
b1111 (
0,
0&
#355000
12
1!
13
b11 5
b11 "
b1101 )
b1101 1
b100100 -
b100 #
b100 .
1,
1&
#360000
1'
1+
b11 (
0,
0&
#365000
02
0!
03
b1101 5
b1101 "
b110 )
b110 1
b100101 -
b101 #
b101 .
1,
1&
#370000
0'
0+
b1101 (
0,
0&
#375000
b1011 5
b1011 "
b11 )
b11 1
b100110 -
b110 #
b110 .
1,
1&
#380000
b1011 (
0,
0&
#385000
12
1!
13
b110 5
b110 "
b1101 )
b1101 1
b100111 -
b111 #
b111 .
1,
1&
#390000
1'
1+
b110 (
0,
0&
#395000
b11 5
b11 "
b11 )
b11 1
b101000 -
b1000 #
b1000 .
1,
1&
#400000
0'
0+
b1101 (
0,
0&
#405000
b1011 )
b1011 1
b101001 -
b1001 #
b1001 .
1,
1&
#410000
1'
1+
b110 (
0,
0&
#415000
b1 5
b1 "
b101 )
b101 1
b101010 -
b1010 #
b1010 .
1,
1&
#420000
b1 (
0,
0&
#425000
02
0!
03
b1111 5
b1111 "
b10 )
b10 1
b101011 -
b1011 #
b1011 .
1,
1&
#430000
0'
0+
b1111 (
0,
0&
#435000
12
1!
13
b1100 5
b1100 "
b1110 )
b1110 1
b101100 -
b1100 #
b1100 .
1,
1&
#440000
1'
1+
b1100 (
0,
0&
#445000
b1101 )
b1101 1
b101101 -
b1101 #
b1101 .
1,
1&
#450000
0,
0&
#455000
b1111 5
b1111 "
b1111 )
b1111 1
b101110 -
b1110 #
b1110 .
1,
1&
#460000
b1111 (
0,
0&
#465000
b100 5
b100 "
b11 )
b11 1
b101111 -
b1111 #
b1111 .
1,
1&
#470000
b100 (
0,
0&
#475000
02
0!
03
b1101 5
b1101 "
b1010 )
b1010 1
b11 $
b11 /
b110000 -
b0 #
b0 .
1,
1&
#480000
0'
0+
b1101 (
0,
0&
#485000
b1110 5
b1110 "
b110001 -
b1 #
b1 .
1,
1&
#490000
b1110 (
0,
0&
#495000
12
1!
13
b1 5
b1 "
b1100 )
b1100 1
b110010 -
b10 #
b10 .
1,
1&
#500000
1'
1+
b1 (
0,
0&
#505000
02
0!
03
b1000 5
b1000 "
b10 )
b10 1
b110011 -
b11 #
b11 .
1,
1&
#510000
0'
0+
b1000 (
0,
0&
#515000
12
1!
13
b1 5
b1 "
b1010 )
b1010 1
b110100 -
b100 #
b100 .
1,
1&
#520000
1'
1+
b1 (
0,
0&
#525000
02
0!
03
b1001 5
b1001 "
b1 )
b1 1
b110101 -
b101 #
b101 .
1,
1&
#530000
0'
0+
b1001 (
0,
0&
#535000
12
1!
13
b1 5
b1 "
b1000 )
b1000 1
b110110 -
b110 #
b110 .
1,
1&
#540000
1'
1+
b1 (
0,
0&
#545000
b10 5
b10 "
b110111 -
b111 #
b111 .
1,
1&
#550000
b10 (
0,
0&
#555000
b11 5
b11 "
b1001 )
b1001 1
b111000 -
b1000 #
b1000 .
1,
1&
#560000
b100 (
0,
0&
#565000
b1011 )
b1011 1
b111001 -
b1001 #
b1001 .
1,
1&
#570000
b111 (
0,
0&
#575000
b110 )
b110 1
b111010 -
b1010 #
b1010 .
1,
1&
#580000
b11 (
0,
0&
#585000
b100 5
b100 "
b111011 -
b1011 #
b1011 .
1,
1&
#590000
b100 (
0,
0&
#595000
b1101 5
b1101 "
b1110 )
b1110 1
b111100 -
b1100 #
b1100 .
1,
1&
#600000
b1101 (
0,
0&
#605000
b1100 5
b1100 "
b1100 )
b1100 1
b111101 -
b1101 #
b1101 .
1,
1&
#610000
b1100 (
0,
0&
#615000
b1011 5
b1011 "
b1010 )
b1010 1
b111110 -
b1110 #
b1110 .
1,
1&
#620000
b1011 (
0,
0&
#625000
b1101 5
b1101 "
b1011 )
b1011 1
b111111 -
b1111 #
b1111 .
1,
1&
#630000
b1101 (
0,
0&
#635000
02
0!
03
b101 5
b101 "
b1 )
b1 1
b100 $
b100 /
b1000000 -
b0 #
b0 .
1,
1&
#640000
0'
0+
b101 (
0,
0&
#645000
b1010 5
b1010 "
b101 )
b101 1
b1000001 -
b1 #
b1 .
1,
1&
#650000
b1010 (
0,
0&
#655000
12
1!
13
b101 5
b101 "
b1111 )
b1111 1
b1000010 -
b10 #
b10 .
1,
1&
#660000
1'
1+
b101 (
0,
0&
#665000
b10 5
b10 "
b1011 )
b1011 1
b1000011 -
b11 #
b11 .
1,
1&
#670000
b10 (
0,
0&
#675000
b1010 )
b1010 1
b1000100 -
b100 #
b100 .
1,
1&
#680000
0,
0&
#685000
b111 5
b111 "
b1110 )
b1110 1
b1000101 -
b101 #
b101 .
1,
1&
#690000
b111 (
0,
0&
#695000
02
0!
03
b1111 5
b1111 "
b101 )
b101 1
b1000110 -
b110 #
b110 .
1,
1&
#700000
0'
0+
b1111 (
0,
0&
#705000
b1100 5
b1100 "
b1 )
b1 1
b1000111 -
b111 #
b111 .
1,
1&
#710000
b1100 (
0,
0&
#715000
b11 5
b11 "
b1001 )
b1001 1
b1001000 -
b1000 #
b1000 .
1,
1&
#720000
1'
1+
b101 (
0,
0&
#725000
b10 )
b10 1
b1001001 -
b1001 #
b1001 .
1,
1&
#730000
0'
0+
b1111 (
0,
0&
#735000
12
1!
13
b1010 5
b1010 "
b1100 )
b1100 1
b1001010 -
b1010 #
b1010 .
1,
1&
#740000
1'
1+
b1010 (
0,
0&
#745000
b1110 5
b1110 "
b1111 )
b1111 1
b1001011 -
b1011 #
b1011 .
1,
1&
#750000
b1110 (
0,
0&
#755000
b1111 5
b1111 "
b1001100 -
b1100 #
b1100 .
1,
1&
#760000
b1111 (
0,
0&
#765000
b1001 5
b1001 "
b1000 )
b1000 1
b1001101 -
b1101 #
b1101 .
1,
1&
#770000
b1001 (
0,
0&
#775000
b111 )
b111 1
b1001110 -
b1110 #
b1110 .
1,
1&
#780000
0,
0&
#785000
14
03
b10 5
b10 "
b1111 )
b1111 1
b1001111 -
b1111 #
b1111 .
1,
1&
#790000
1*
0+
b10 (
0,
0&
#795000
04
13
b1 5
b1 "
b1100 )
b1100 1
b101 $
b101 /
b1010000 -
b0 #
b0 .
1,
1&
#800000
0*
1+
b1 (
0,
0&
#805000
b1011 )
b1011 1
b1010001 -
b1 #
b1 .
1,
1&
#810000
0,
0&
#815000
b0 5
b0 "
b1001 )
b1001 1
b1010010 -
b10 #
b10 .
1,
1&
#820000
b0 (
0,
0&
#825000
b1 5
b1 "
b1010011 -
b11 #
b11 .
1,
1&
#830000
b1 (
0,
0&
#835000
02
0!
03
b1001 5
b1001 "
b0 )
b0 1
b1010100 -
b100 #
b100 .
1,
1&
#840000
0'
0+
b1001 (
0,
0&
#845000
12
1!
13
b1 5
b1 "
b111 )
b111 1
b1010101 -
b101 #
b101 .
1,
1&
#850000
1'
1+
b1 (
0,
0&
#855000
02
0!
03
b1100 5
b1100 "
b1 )
b1 1
b1010110 -
b110 #
b110 .
1,
1&
#860000
0'
0+
b1100 (
0,
0&
#865000
12
1!
13
b10 5
b10 "
b110 )
b110 1
b1010111 -
b111 #
b111 .
1,
1&
#870000
1'
1+
b10 (
0,
0&
#875000
b11 5
b11 "
b1100 )
b1100 1
b1011000 -
b1000 #
b1000 .
1,
1&
#880000
b1001 (
0,
0&
#885000
b10 )
b10 1
b1011001 -
b1001 #
b1001 .
1,
1&
#890000
b0 (
0,
0&
#895000
b111 5
b111 "
b1000 )
b1000 1
b1011010 -
b1010 #
b1010 .
1,
1&
#900000
b111 (
0,
0&
#905000
b111 )
b111 1
b1011011 -
b1011 #
b1011 .
1,
1&
#910000
0,
0&
#915000
b1110 5
b1110 "
b1101 )
b1101 1
b1011100 -
b1100 #
b1100 .
1,
1&
#920000
b1110 (
0,
0&
#925000
b100 5
b100 "
b10 )
b10 1
b1011101 -
b1101 #
b1101 .
1,
1&
#930000
b100 (
0,
0&
#935000
14
03
b1 5
b1 "
b1110 )
b1110 1
b1011110 -
b1110 #
b1110 .
1,
1&
#940000
1*
0+
b1 (
0,
0&
#945000
b1101 )
b1101 1
b1011111 -
b1111 #
b1111 .
1,
1&
#950000
0,
0&
#955000
02
0!
04
b1111 5
b1111 "
b1001 )
b1001 1
b110 $
b110 /
b1100000 -
b0 #
b0 .
1,
1&
#960000
0'
0*
b1111 (
0,
0&
#965000
12
1!
13
b110 5
b110 "
b1111 )
b1111 1
b1100001 -
b1 #
b1 .
1,
1&
#970000
1'
1+
b110 (
0,
0&
#975000
02
0!
03
b1011 5
b1011 "
b11 )
b11 1
b1100010 -
b10 #
b10 .
1,
1&
#980000
0'
0+
b1011 (
0,
0&
#985000
b1110 5
b1110 "
b101 )
b101 1
b1100011 -
b11 #
b11 .
1,
1&
#990000
b1110 (
0,
0&
#995000
12
1!
13
b10 5
b10 "
b1000 )
b1000 1
b1100100 -
b100 #
b100 .
1,
1&
#1000000
1'
1+
b10 (
0,
0&
#1005000
b11 5
b11 "
b1100101 -
b101 #
b101 .
1,
1&
